calculadora_avancada_color/__init__.py
calculadora_avancada_color/calculadora_avancada_color.py
calculadora_avancada_color-1.0.0.dist-info/licenses/LICENSE
calculadora_avancada_color-1.0.0.dist-info/METADATA
calculadora_avancada_color-1.0.0.dist-info/WHEEL
calculadora_avancada_color-1.0.0.dist-info/top_level.txt
calculadora_avancada_color-1.0.0.dist-info/RECORD
