Metadata-Version: 2.4
Name: calculadora-avancada-color
Version: 1.0.0
Summary: Uma calculadora avançada com cores no terminal
Author-email: Seu Nome <seu@email.com>
License: MIT
Project-URL: Homepage, https://github.com/Lgb145483/calculadora
Project-URL: Repository, https://github.com/Lgb145483/calculadora
Project-URL: Changelog, https://github.com/Lgb145483/calculadora/blob/main/CHANGELOG.md
Requires-Python: >=3.10
License-File: LICENSE
Dynamic: license-file
